pyindia_zipcode/Store.db
pyindia_zipcode/__init__.py
pyindia_zipcode/utils.py
pyindia_zipcode-0.0.2.data/data/Store/Store.db
pyindia_zipcode-0.0.2.dist-info/LICENSE
pyindia_zipcode-0.0.2.dist-info/METADATA
pyindia_zipcode-0.0.2.dist-info/WHEEL
pyindia_zipcode-0.0.2.dist-info/top_level.txt
pyindia_zipcode-0.0.2.dist-info/zip-safe
pyindia_zipcode-0.0.2.dist-info/RECORD
